LICENSE
MANIFEST.in
README.md
requirements.txt
setup.py
bin/fetch-mcgill-transcript
mcgill_minerva.egg-info/PKG-INFO
mcgill_minerva.egg-info/SOURCES.txt
mcgill_minerva.egg-info/dependency_links.txt
mcgill_minerva.egg-info/requires.txt
mcgill_minerva.egg-info/top_level.txt
minerva/__init__.py
minerva/client.py
minerva/transcript.py