Metadata-Version: 1.1
Name: mcgill-minerva
Version: 0.1.0
Summary: Client library for McGill Minerva.
Home-page: https://github.com/isbadawi/minerva
Author: Ismail Badawi
Author-email: isbadawi@gmail.com
License: MIT
Platform: UNKNOWN
Classifier: Development Status :: 3 - Alpha
Classifier: Intended Audience :: Developers
Classifier: License :: OSI Approved :: MIT License
Classifier: Programming Language :: Python :: 2.7
Classifier: Topic :: Software Development :: Libraries :: Python Modules
Classifier: Topic :: Utilities
